smallgenomeutilities/__checkPath__.py
smallgenomeutilities/__init__.py
smallgenomeutilities/__mapper_impl__.py
smallgenomeutilities/__pileup__.py
smallgenomeutilities/_version.py
smallgenomeutilities-0.5.2.data/scripts/aln2basecnt
smallgenomeutilities-0.5.2.data/scripts/compute_mds
smallgenomeutilities-0.5.2.data/scripts/convert_qr
smallgenomeutilities-0.5.2.data/scripts/convert_reference
smallgenomeutilities-0.5.2.data/scripts/coverage
smallgenomeutilities-0.5.2.data/scripts/coverage_depth_qc
smallgenomeutilities-0.5.2.data/scripts/coverage_stats
smallgenomeutilities-0.5.2.data/scripts/extract_consensus
smallgenomeutilities-0.5.2.data/scripts/extract_coverage_intervals
smallgenomeutilities-0.5.2.data/scripts/extract_sam
smallgenomeutilities-0.5.2.data/scripts/extract_seq
smallgenomeutilities-0.5.2.data/scripts/frameshift_deletions_checks
smallgenomeutilities-0.5.2.data/scripts/gather_coverage
smallgenomeutilities-0.5.2.data/scripts/mapper
smallgenomeutilities-0.5.2.data/scripts/min_coverage
smallgenomeutilities-0.5.2.data/scripts/minority_freq
smallgenomeutilities-0.5.2.data/scripts/pair_sequences
smallgenomeutilities-0.5.2.data/scripts/paired_end_read_merger
smallgenomeutilities-0.5.2.data/scripts/predict_num_reads
smallgenomeutilities-0.5.2.data/scripts/prepare_primers
smallgenomeutilities-0.5.2.data/scripts/remove_gaps_msa
smallgenomeutilities-0.5.2.dist-info/licenses/LICENSE
smallgenomeutilities-0.5.2.dist-info/METADATA
smallgenomeutilities-0.5.2.dist-info/WHEEL
smallgenomeutilities-0.5.2.dist-info/top_level.txt
smallgenomeutilities-0.5.2.dist-info/RECORD
