Metadata-Version: 2.4
Name: smallgenomeutilities
Version: 0.5.2
Summary: A collection of scripts that are useful for dealing with viral RNA NGS data.
Author-email: David Seifert <david.seifert@bsse.ethz.ch>, Susana Posada Cespedes <susana.posada@bsse.ethz.ch>, Ivan Topolsky <ivan.topolsky@sib.swiss>, Lara Fuhrmann <lara.fuhrmann@bsse.ethz.ch>, Matteo Carrara <carrara@nexus.ethz.ch>, Michal Okoniewski <michal.okoniewski@gmail.com>, "Gordon J. Köhn" <gordon.koehn@dbsse.ethz.ch>
Maintainer-email: Ivan Topolsky <ivan.topolsky@sib.swiss>, "Gordon J. Köhn" <gordon.koehn@dbsse.ethz.ch>, Matteo Carrara <carrara@nexus.ethz.ch>
License-Expression: GPL-2.0-or-later
Project-URL: Repository, https://github.com/cbg-ethz/smallgenomeutilities
Keywords: NGS,SAM,BAM,CRAM,HIV-1,SARS-CoV-2,alignment
Classifier: Development Status :: 3 - Alpha
Classifier: Topic :: Scientific/Engineering :: Bio-Informatics
Classifier: Topic :: Utilities
Classifier: Programming Language :: Python :: 3
Classifier: Programming Language :: Python :: 3.7
Classifier: Programming Language :: Python :: 3.8
Classifier: Programming Language :: Python :: 3.9
Classifier: Programming Language :: Python :: 3.10
Requires-Python: >=3.7
License-File: LICENSE
Requires-Dist: biopython==1.85
Requires-Dist: bcbio-gff
Requires-Dist: pysam>=0.23
Requires-Dist: pysamstats
Requires-Dist: pandas
Requires-Dist: numpy
Requires-Dist: scipy
Requires-Dist: scikit-learn
Requires-Dist: matplotlib
Requires-Dist: progress
Requires-Dist: pyyaml
Requires-Dist: more-itertools
Provides-Extra: test
Requires-Dist: pytest; extra == "test"
Dynamic: license-file
